tpDccLib/__init__.py
tpDccLib/abstract/__init__.py
tpDccLib/abstract/callback.py
tpDccLib/abstract/dcc.py
tpDccLib/abstract/menu.py
tpDccLib/abstract/progressbar.py
tpDccLib/abstract/shelf.py
tpDccLib/core/__init__.py
tpDccLib/core/consts.py
tpDccLib/core/data.py
tpDccLib/core/dcc.py
tpDccLib/core/exceptions.py
tpDccLib/core/node.py
tpDccLib/core/project.py
tpDccLib/core/scripts.py
tpdcclib-0.0.3.dist-info/LICENSE
tpdcclib-0.0.3.dist-info/METADATA
tpdcclib-0.0.3.dist-info/WHEEL
tpdcclib-0.0.3.dist-info/top_level.txt
tpdcclib-0.0.3.dist-info/RECORD
