Metadata-Version: 2.1
Name: tpdcclib
Version: 0.0.3
Summary: Collection of Python modules to write DCC tools in a DCC agnostic way.
Home-page: https://github.com/tpoveda/tpDccLib
Author: Tomas Poveda
Author-email: tpovedatd@gmail.com
License: MIT
Platform: UNKNOWN
Requires-Dist: tpPyUtils
Provides-Extra: dev
Requires-Dist: wheel ; extra == 'dev'
Provides-Extra: test
Requires-Dist: pytest ; extra == 'test'
